ros_sensor_topic/__init__.py
ros_sensor_topic/script.py
ros_sensor_topic-0.3.2.dist-info/METADATA
ros_sensor_topic-0.3.2.dist-info/WHEEL
ros_sensor_topic-0.3.2.dist-info/top_level.txt
ros_sensor_topic-0.3.2.dist-info/RECORD
