Metadata-Version: 2.1
Name: ros-sensor-topic
Version: 0.3.2
Summary: A utility package to find ROS topic names for color and depth streams.
Home-page: https://github.com/katrinmisel/ros_sensor_topic
Author: Katrin-Misel Ponomarjova
Author-email: katrinmisel@gmail.com
License: UNKNOWN
Platform: UNKNOWN
Classifier: Programming Language :: Python :: 3
Classifier: License :: OSI Approved :: MIT License
Classifier: Operating System :: OS Independent
Requires-Python: >=3.6
